setup.py
fondasms/__init__.py
fondasms/stub.py
fondasms/urls.py
fondasms/utils.py
fondasms/views.py
fondasms.egg-info/PKG-INFO
fondasms.egg-info/SOURCES.txt
fondasms.egg-info/dependency_links.txt
fondasms.egg-info/top_level.txt