Metadata-Version: 1.1
Name: fondasms
Version: 0.2
Summary: Django app to add support for FondaSMS requests.
Home-page: http://github.com/yeleman/django-fondasms
Author: yeleman
Author-email: rgaudin@gmail.com
License: UNKNOWN
Platform: UNKNOWN
Classifier: Development Status :: 4 - Beta
Classifier: Intended Audience :: Developers
Classifier: License :: OSI Approved :: BSD License
Classifier: Programming Language :: Python
Classifier: Programming Language :: Python :: 2.7
Classifier: Programming Language :: Python :: 3.3
